MANIFEST.in
README
setup.py
scalpel/__init__.py
scalpel/app.py
scalpel/clipboard.py
scalpel/constants.py
scalpel/control.py
scalpel/cursor.py
scalpel/edit.py
scalpel/effect.py
scalpel/event.py
scalpel/graphmodel.py
scalpel/gtkeffect.py
scalpel/gtkfiledialog.py
scalpel/gtkui.py
scalpel/gtkwaveform.py
scalpel/mock.py
scalpel/player.py
scalpel/pysndfile.py
scalpel/run.py
scalpel/selection.py
scalpel.egg-info/PKG-INFO
scalpel.egg-info/SOURCES.txt
scalpel.egg-info/dependency_links.txt
scalpel.egg-info/requires.txt
scalpel.egg-info/top_level.txt
scalpel/fast/fast.c
scalpel/fast/fast.h
scalpel/fx/__init__.py
scalpel/fx/_svf.c
scalpel/fx/bitcrusher.py
scalpel/fx/convolution.py
scalpel/fx/monoize.py
scalpel/fx/svf.py
scalpel/fx/volume.py
scripts/scalpel