Metadata-Version: 1.1
Name: scalpel
Version: 0.8.0
Summary: Scalpel Audio Editor
Home-page: http://scalpelsound.online.fr
Author: Pierre
Author-email: stackp@online.fr
License: BSD License
Platform: UNKNOWN
Classifier: Development Status :: 3 - Alpha
Classifier: Environment :: X11 Applications :: GTK
Classifier: Intended Audience :: End Users/Desktop
Classifier: License :: OSI Approved :: BSD License
Classifier: Natural Language :: English
Classifier: Operating System :: POSIX :: Linux
Classifier: Programming Language :: Python
Classifier: Topic :: Multimedia :: Sound/Audio :: Editors
Requires: PyGTK
Requires: numpy
Requires: pyalsaaudio (>=0.6)
